TIPLSB/__init__.py
TIPLSB/class_tiplsb.py
TIPLSB/config.py
TIPLSB/function_additional.py
TIPLSB/function_decrypt.py
TIPLSB-0.0.1.dist-info/LICENSE.txt
TIPLSB-0.0.1.dist-info/METADATA
TIPLSB-0.0.1.dist-info/WHEEL
TIPLSB-0.0.1.dist-info/top_level.txt
TIPLSB-0.0.1.dist-info/RECORD
