Metadata-Version: 2.1
Name: TIPLSB
Version: 0.0.1
Summary: Library to trace the path of an image based on LSB and RSA.
Home-page: https://github.com/brunogonzalezlla/TIPLSBlib
Download-URL: https://github.com/brunogonzalezlla/TIPLSBlib/archive/v0.1.tar.gz
Author: Bruno González
Author-email: brunogllaga@icloud.com
License: MIT
Classifier: Programming Language :: Python
Classifier: Programming Language :: Python :: 2.7
Classifier: Programming Language :: Python :: 3.3
Classifier: Programming Language :: Python :: 3.4
Classifier: Programming Language :: Python :: 3.5
Classifier: Programming Language :: Python :: 3.6
Classifier: Programming Language :: Python :: 3.7
License-File: LICENSE.txt
Requires-Dist: Pillow
Requires-Dist: numpy
